<?xml version="1.0" encoding="UTF-8" standalone="no"?>
<Farmacia>
    <Medicamento>
        <id>1</id>
        <nombre>Aspirina1</nombre>
        <precio>50.0</precio>
        <stock>50</stock>
        <stockMaximo>50</stockMaximo>
        <stockMinimo>50</stockMinimo>
    </Medicamento>
    <Medicamento>
        <id>2</id>
        <nombre>Aspirina2</nombre>
        <precio>50.0</precio>
        <stock>50</stock>
        <stockMaximo>50</stockMaximo>
        <stockMinimo>50</stockMinimo>
    </Medicamento>
    <Medicamento>
        <id>3</id>
        <nombre>Aspirina3</nombre>
        <precio>50.0</precio>
        <stock>50</stock>
        <stockMaximo>50</stockMaximo>
        <stockMinimo>50</stockMinimo>
    </Medicamento>
    <Medicamento>
        <id>4</id>
        <nombre>Aspirina4</nombre>
        <precio>50.0</precio>
        <stock>50</stock>
        <stockMaximo>50</stockMaximo>
        <stockMinimo>50</stockMinimo>
    </Medicamento>
    <Medicamento>
        <id>5</id>
        <nombre>Aspirina5</nombre>
        <precio>50.0</precio>
        <stock>50</stock>
        <stockMaximo>50</stockMaximo>
        <stockMinimo>50</stockMinimo>
    </Medicamento>
    <Medicamento>
        <id>6</id>
        <nombre>Aspirina6</nombre>
        <precio>50.0</precio>
        <stock>50</stock>
        <stockMaximo>50</stockMaximo>
        <stockMinimo>50</stockMinimo>
    </Medicamento>
    <Medicamento>
        <id>7</id>
        <nombre>Aspirina7</nombre>
        <precio>50.0</precio>
        <stock>50</stock>
        <stockMaximo>50</stockMaximo>
        <stockMinimo>50</stockMinimo>
    </Medicamento>
    <Medicamento>
        <id>8</id>
        <nombre>Aspirina8</nombre>
        <precio>50.0</precio>
        <stock>50</stock>
        <stockMaximo>50</stockMaximo>
        <stockMinimo>50</stockMinimo>
    </Medicamento>
    <Medicamento>
        <id>9</id>
        <nombre>Aspirina9</nombre>
        <precio>50.0</precio>
        <stock>50</stock>
        <stockMaximo>50</stockMaximo>
        <stockMinimo>50</stockMinimo>
    </Medicamento>
    <Medicamento>
        <id>10</id>
        <nombre>Aspirina10</nombre>
        <precio>50.0</precio>
        <stock>50</stock>
        <stockMaximo>50</stockMaximo>
        <stockMinimo>50</stockMinimo>
    </Medicamento>
</Farmacia>
